fsspec/_version.py
fspec-2024.3.1.dist-info/METADATA
fspec-2024.3.1.dist-info/WHEEL
fspec-2024.3.1.dist-info/licenses/LICENSE
fspec-2024.3.1.dist-info/RECORD
