Metadata-Version: 2.3
Name: fspec
Version: 2024.3.1
Summary: File-system specification
Project-URL: Changelog, https://filesystem-spec.readthedocs.io/en/latest/changelog.html
Project-URL: Documentation, https://filesystem-spec.readthedocs.io/en/latest/
Project-URL: Homepage, https://github.com/fsspec/filesystem_spec
Maintainer-email: Martin Durant <mdurant@anaconda.com>
License: BSD 3-Clause License
License-File: LICENSE
Keywords: file
Classifier: Development Status :: 4 - Beta
Classifier: Intended Audience :: Developers
Classifier: License :: OSI Approved :: BSD License
Classifier: Operating System :: OS Independent
Classifier: Programming Language :: Python :: 3.8
Classifier: Programming Language :: Python :: 3.9
Classifier: Programming Language :: Python :: 3.10
Classifier: Programming Language :: Python :: 3.11
Classifier: Programming Language :: Python :: 3.12
Requires-Python: >=3.8
Provides-Extra: abfs
Requires-Dist: adlfs; extra == 'abfs'
Provides-Extra: adl
Requires-Dist: adlfs; extra == 'adl'
Provides-Extra: arrow
Requires-Dist: pyarrow>=1; extra == 'arrow'
Provides-Extra: dask
Requires-Dist: dask; extra == 'dask'
Requires-Dist: distributed; extra == 'dask'
Provides-Extra: dev
Requires-Dist: pre-commit; extra == 'dev'
Requires-Dist: ruff; extra == 'dev'
Provides-Extra: dropbox
Requires-Dist: dropbox; extra == 'dropbox'
Requires-Dist: dropboxdrivefs; extra == 'dropbox'
Requires-Dist: requests; extra == 'dropbox'
Provides-Extra: entrypoints
Provides-Extra: full
Requires-Dist: adlfs; extra == 'full'
Requires-Dist: aiohttp!=4.0.0a0,!=4.0.0a1; extra == 'full'
Requires-Dist: dask; extra == 'full'
Requires-Dist: distributed; extra == 'full'
Requires-Dist: dropbox; extra == 'full'
Requires-Dist: dropboxdrivefs; extra == 'full'
Requires-Dist: fusepy; extra == 'full'
Requires-Dist: gcsfs; extra == 'full'
Requires-Dist: libarchive-c; extra == 'full'
Requires-Dist: ocifs; extra == 'full'
Requires-Dist: panel; extra == 'full'
Requires-Dist: paramiko; extra == 'full'
Requires-Dist: pyarrow>=1; extra == 'full'
Requires-Dist: pygit2; extra == 'full'
Requires-Dist: requests; extra == 'full'
Requires-Dist: s3fs; extra == 'full'
Requires-Dist: smbprotocol; extra == 'full'
Requires-Dist: tqdm; extra == 'full'
Provides-Extra: fuse
Requires-Dist: fusepy; extra == 'fuse'
Provides-Extra: gcs
Requires-Dist: gcsfs; extra == 'gcs'
Provides-Extra: git
Requires-Dist: pygit2; extra == 'git'
Provides-Extra: github
Requires-Dist: requests; extra == 'github'
Provides-Extra: gs
Requires-Dist: gcsfs; extra == 'gs'
Provides-Extra: gui
Requires-Dist: panel; extra == 'gui'
Provides-Extra: hdfs
Requires-Dist: pyarrow>=1; extra == 'hdfs'
Provides-Extra: http
Requires-Dist: aiohttp!=4.0.0a0,!=4.0.0a1; extra == 'http'
Provides-Extra: libarchive
Requires-Dist: libarchive-c; extra == 'libarchive'
Provides-Extra: oci
Requires-Dist: ocifs; extra == 'oci'
Provides-Extra: s3
Requires-Dist: s3fs; extra == 's3'
Provides-Extra: sftp
Requires-Dist: paramiko; extra == 'sftp'
Provides-Extra: smb
Requires-Dist: smbprotocol; extra == 'smb'
Provides-Extra: ssh
Requires-Dist: paramiko; extra == 'ssh'
Provides-Extra: test
Requires-Dist: aiohttp!=4.0.0a0,!=4.0.0a1; extra == 'test'
Requires-Dist: numpy; extra == 'test'
Requires-Dist: pytest; extra == 'test'
Requires-Dist: pytest-asyncio!=0.22.0; extra == 'test'
Requires-Dist: pytest-benchmark; extra == 'test'
Requires-Dist: pytest-cov; extra == 'test'
Requires-Dist: pytest-mock; extra == 'test'
Requires-Dist: pytest-recording; extra == 'test'
Requires-Dist: pytest-rerunfailures; extra == 'test'
Requires-Dist: requests; extra == 'test'
Provides-Extra: test-downstream
Requires-Dist: aiobotocore<3.0.0,>=2.5.4; extra == 'test-downstream'
Requires-Dist: dask-expr; extra == 'test-downstream'
Requires-Dist: dask[dataframe,test]; extra == 'test-downstream'
Requires-Dist: moto[server]<5,>4; extra == 'test-downstream'
Requires-Dist: pytest-timeout; extra == 'test-downstream'
Requires-Dist: xarray; extra == 'test-downstream'
Provides-Extra: test-full
Requires-Dist: adlfs; extra == 'test-full'
Requires-Dist: aiohttp!=4.0.0a0,!=4.0.0a1; extra == 'test-full'
Requires-Dist: cloudpickle; extra == 'test-full'
Requires-Dist: dask; extra == 'test-full'
Requires-Dist: distributed; extra == 'test-full'
Requires-Dist: dropbox; extra == 'test-full'
Requires-Dist: dropboxdrivefs; extra == 'test-full'
Requires-Dist: fastparquet; extra == 'test-full'
Requires-Dist: fusepy; extra == 'test-full'
Requires-Dist: gcsfs; extra == 'test-full'
Requires-Dist: jinja2; extra == 'test-full'
Requires-Dist: kerchunk; extra == 'test-full'
Requires-Dist: libarchive-c; extra == 'test-full'
Requires-Dist: lz4; extra == 'test-full'
Requires-Dist: notebook; extra == 'test-full'
Requires-Dist: numpy; extra == 'test-full'
Requires-Dist: ocifs; extra == 'test-full'
Requires-Dist: pandas; extra == 'test-full'
Requires-Dist: panel; extra == 'test-full'
Requires-Dist: paramiko; extra == 'test-full'
Requires-Dist: pyarrow; extra == 'test-full'
Requires-Dist: pyarrow>=1; extra == 'test-full'
Requires-Dist: pyftpdlib; extra == 'test-full'
Requires-Dist: pygit2; extra == 'test-full'
Requires-Dist: pytest; extra == 'test-full'
Requires-Dist: pytest-asyncio!=0.22.0; extra == 'test-full'
Requires-Dist: pytest-benchmark; extra == 'test-full'
Requires-Dist: pytest-cov; extra == 'test-full'
Requires-Dist: pytest-mock; extra == 'test-full'
Requires-Dist: pytest-recording; extra == 'test-full'
Requires-Dist: pytest-rerunfailures; extra == 'test-full'
Requires-Dist: python-snappy; extra == 'test-full'
Requires-Dist: requests; extra == 'test-full'
Requires-Dist: smbprotocol; extra == 'test-full'
Requires-Dist: tqdm; extra == 'test-full'
Requires-Dist: urllib3; extra == 'test-full'
Requires-Dist: zarr; extra == 'test-full'
Requires-Dist: zstandard; extra == 'test-full'
Provides-Extra: tqdm
Requires-Dist: tqdm; extra == 'tqdm'
